{
  "name": "Amulet of glory(t1)",
  "desc": "A very powerful dragonstone amulet.",
  "members": false,
  "tradable": true,
  "asNonStackable": 10360,
  "asStackable": 10361,
  "value": 10400000,
  "highAlch": 11000000,
  "lowAlch": 9900000,
  "weight": 0.0,
  "equipSlot": 2,
  "stabAttackBonus": 10,
  "slashAttackBonus": 10,
  "crushAttackBonus": 10,
  "magicAttackBonus": 10,
  "rangedAttackBonus": 10,
  "stabDefenceBonus": 3,
  "slashDefenceBonus": 3,
  "crushDefenceBonus": 3,
  "magicDefenceBonus": 3,
  "rangedDefenceBonus": 3,
  "strengthBonus": 6,
  "prayerBonus": 0
}