{
  "name": "Fighter torso",
  "desc": "Penance Fighter torso armour.",
  "members": false,
  "tradable": true,
  "asNonStackable": 10551,
  "asStackable": -1,
  "value": 12700,
  "highAlch": 6000,
  "lowAlch": 4000,
  "weight": 0.0,
  "equipSlot": 4,
  "stabAttackBonus": 0,
  "slashAttackBonus": 0,
  "crushAttackBonus": 0,
  "magicAttackBonus": -40,
  "rangedAttackBonus": 0,
  "stabDefenceBonus": 62,
  "slashDefenceBonus": 85,
  "crushDefenceBonus": 62,
  "magicDefenceBonus": -10,
  "rangedDefenceBonus": 67,
  "strengthBonus": 4,
  "prayerBonus": 0
}